{
  "generated_at": "2026-06-29T05:49:12.491714+00:00",
  "hourly": {
    "precipitation_probability": [
      0,
      0,
      0,
      0,
      0,
      0,
      0,
      0,
      0,
      0,
      0,
      0,
      0,
      0,
      0,
      0,
      0,
      0,
      0,
      0,
      0,
      0,
      0,
      0,
      0,
      0,
      0,
      0,
      0,
      0,
      0,
      0,
      0,
      0,
      0,
      0,
      0,
      0,
      0,
      0,
      0,
      0,
      0,
      0,
      0,
      0,
      0,
      0,
      0,
      0,
      0,
      0,
      0,
      0,
      0,
      0,
      0,
      0,
      0,
      0,
      0,
      10,
      10,
      10,
      10,
      10,
      10,
      14,
      14,
      14,
      14,
      14,
      14,
      3,
      3,
      3,
      3,
      3,
      3,
      1,
      1,
      1,
      1,
      1,
      1,
      4,
      4,
      4,
      4,
      4,
      4,
      9,
      9,
      9,
      9,
      9,
      9,
      11,
      11,
      11,
      11,
      11,
      11,
      1,
      1,
      1,
      1,
      1,
      1,
      5,
      5,
      5,
      5,
      5,
      5,
      3,
      3,
      3,
      3,
      3,
      3,
      3,
      3,
      3,
      3,
      3,
      3,
      0,
      0,
      0,
      0,
      0,
      0,
      2,
      2,
      2,
      2,
      2,
      2,
      4,
      4,
      4,
      4,
      4,
      4,
      0,
      0,
      0,
      0,
      0,
      0,
      0,
      0,
      0,
      0,
      0,
      0,
      6,
      6,
      6,
      6,
      6,
      6,
      6,
      6,
      6,
      6,
      6,
      6,
      5,
      5,
      5,
      5,
      5,
      5,
      3,
      3,
      3,
      3,
      3,
      3,
      22,
      22,
      22,
      22,
      22,
      22,
      19,
      19,
      19,
      19,
      19,
      19,
      3,
      3,
      3,
      3,
      3,
      3,
      0,
      0,
      0,
      0,
      0,
      0,
      17,
      17,
      17,
      17,
      17,
      17,
      18,
      18,
      18,
      18,
      18,
      18,
      2,
      2,
      2,
      2,
      2,
      2,
      1,
      1,
      1,
      1,
      1,
      1,
      28,
      28,
      28,
      28,
      28,
      28,
      16,
      16,
      16,
      16,
      16
    ],
    "temperature_2m": [
      73.0,
      66.1,
      63.7,
      62.8,
      61.8,
      57.8,
      56.7,
      60.3,
      65.3,
      69.5,
      73.2,
      75.1,
      77.9,
      79.6,
      81.2,
      83.9,
      84.8,
      86.4,
      85.6,
      83.9,
      81.2,
      75.5,
      72.1,
      69.5,
      69.0,
      66.5,
      64.0,
      61.6,
      59.6,
      57.8,
      56.6,
      59.9,
      64.0,
      68.5,
      72.4,
      76.8,
      81.9,
      83.0,
      83.6,
      84.7,
      85.5,
      85.8,
      85.0,
      83.3,
      79.4,
      74.9,
      70.9,
      67.9,
      64.2,
      61.1,
      58.8,
      58.4,
      56.9,
      53.4,
      52.4,
      56.0,
      63.0,
      68.9,
      75.3,
      81.4,
      88.1,
      90.5,
      92.3,
      93.7,
      90.1,
      86.9,
      86.4,
      76.9,
      74.8,
      72.3,
      72.1,
      72.3,
      69.7,
      68.1,
      65.4,
      63.6,
      62.5,
      62.0,
      61.6,
      66.7,
      72.3,
      77.3,
      81.6,
      84.7,
      89.7,
      92.1,
      92.8,
      93.0,
      93.3,
      91.3,
      88.8,
      84.9,
      81.4,
      77.8,
      74.6,
      77.3,
      72.8,
      70.3,
      67.0,
      65.6,
      64.2,
      61.6,
      61.8,
      66.3,
      71.9,
      78.2,
      82.7,
      87.2,
      91.0,
      93.3,
      94.4,
      95.5,
      96.0,
      94.9,
      92.4,
      91.7,
      84.9,
      79.6,
      77.3,
      78.0,
      74.4,
      71.7,
      71.0,
      71.5,
      69.6,
      66.0,
      64.7,
      69.7,
      75.5,
      81.3,
      85.4,
      89.2,
      92.8,
      94.9,
      96.9,
      98.5,
      98.2,
      97.5,
      96.2,
      93.1,
      88.8,
      84.9,
      81.3,
      77.8,
      75.3,
      74.3,
      74.2,
      73.9,
      72.3,
      70.6,
      70.6,
      74.2,
      79.7,
      84.5,
      87.6,
      89.9,
      91.7,
      93.5,
      94.9,
      94.4,
      90.8,
      85.4,
      80.7,
      78.0,
      76.1,
      74.1,
      71.4,
      68.5,
      65.8,
      63.2,
      60.7,
      59.1,
      58.3,
      58.2,
      59.8,
      63.8,
      69.4,
      75.0,
      80.5,
      85.9,
      90.3,
      93.5,
      95.6,
      94.8,
      88.8,
      80.0,
      73.2,
      70.6,
      70.0,
      69.6,
      68.9,
      68.5,
      67.6,
      65.6,
      63.2,
      61.3,
      60.2,
      59.7,
      60.6,
      63.4,
      67.4,
      72.1,
      77.4,
      83.2,
      88.3,
      92.5,
      96.1,
      98.4,
      99.5,
      99.4,
      96.9,
      90.2,
      81.2,
      74.2,
      71.7,
      71.4,
      71.0,
      69.8,
      68.7,
      67.4,
      65.4,
      63.4,
      63.6,
      67.7,
      74.0,
      80.4,
      86.7,
      93.1,
      98.0,
      100.8,
      102.0,
      102.0,
      100.7,
      98.3,
      94.8,
      89.5,
      83.1,
      78.0,
      75.6,
      74.6
    ],
    "time": [
      "2026-06-28T00:00",
      "2026-06-28T01:00",
      "2026-06-28T02:00",
      "2026-06-28T03:00",
      "2026-06-28T04:00",
      "2026-06-28T05:00",
      "2026-06-28T06:00",
      "2026-06-28T07:00",
      "2026-06-28T08:00",
      "2026-06-28T09:00",
      "2026-06-28T10:00",
      "2026-06-28T11:00",
      "2026-06-28T12:00",
      "2026-06-28T13:00",
      "2026-06-28T14:00",
      "2026-06-28T15:00",
      "2026-06-28T16:00",
      "2026-06-28T17:00",
      "2026-06-28T18:00",
      "2026-06-28T19:00",
      "2026-06-28T20:00",
      "2026-06-28T21:00",
      "2026-06-28T22:00",
      "2026-06-28T23:00",
      "2026-06-29T00:00",
      "2026-06-29T01:00",
      "2026-06-29T02:00",
      "2026-06-29T03:00",
      "2026-06-29T04:00",
      "2026-06-29T05:00",
      "2026-06-29T06:00",
      "2026-06-29T07:00",
      "2026-06-29T08:00",
      "2026-06-29T09:00",
      "2026-06-29T10:00",
      "2026-06-29T11:00",
      "2026-06-29T12:00",
      "2026-06-29T13:00",
      "2026-06-29T14:00",
      "2026-06-29T15:00",
      "2026-06-29T16:00",
      "2026-06-29T17:00",
      "2026-06-29T18:00",
      "2026-06-29T19:00",
      "2026-06-29T20:00",
      "2026-06-29T21:00",
      "2026-06-29T22:00",
      "2026-06-29T23:00",
      "2026-06-30T00:00",
      "2026-06-30T01:00",
      "2026-06-30T02:00",
      "2026-06-30T03:00",
      "2026-06-30T04:00",
      "2026-06-30T05:00",
      "2026-06-30T06:00",
      "2026-06-30T07:00",
      "2026-06-30T08:00",
      "2026-06-30T09:00",
      "2026-06-30T10:00",
      "2026-06-30T11:00",
      "2026-06-30T12:00",
      "2026-06-30T13:00",
      "2026-06-30T14:00",
      "2026-06-30T15:00",
      "2026-06-30T16:00",
      "2026-06-30T17:00",
      "2026-06-30T18:00",
      "2026-06-30T19:00",
      "2026-06-30T20:00",
      "2026-06-30T21:00",
      "2026-06-30T22:00",
      "2026-06-30T23:00",
      "2026-07-01T00:00",
      "2026-07-01T01:00",
      "2026-07-01T02:00",
      "2026-07-01T03:00",
      "2026-07-01T04:00",
      "2026-07-01T05:00",
      "2026-07-01T06:00",
      "2026-07-01T07:00",
      "2026-07-01T08:00",
      "2026-07-01T09:00",
      "2026-07-01T10:00",
      "2026-07-01T11:00",
      "2026-07-01T12:00",
      "2026-07-01T13:00",
      "2026-07-01T14:00",
      "2026-07-01T15:00",
      "2026-07-01T16:00",
      "2026-07-01T17:00",
      "2026-07-01T18:00",
      "2026-07-01T19:00",
      "2026-07-01T20:00",
      "2026-07-01T21:00",
      "2026-07-01T22:00",
      "2026-07-01T23:00",
      "2026-07-02T00:00",
      "2026-07-02T01:00",
      "2026-07-02T02:00",
      "2026-07-02T03:00",
      "2026-07-02T04:00",
      "2026-07-02T05:00",
      "2026-07-02T06:00",
      "2026-07-02T07:00",
      "2026-07-02T08:00",
      "2026-07-02T09:00",
      "2026-07-02T10:00",
      "2026-07-02T11:00",
      "2026-07-02T12:00",
      "2026-07-02T13:00",
      "2026-07-02T14:00",
      "2026-07-02T15:00",
      "2026-07-02T16:00",
      "2026-07-02T17:00",
      "2026-07-02T18:00",
      "2026-07-02T19:00",
      "2026-07-02T20:00",
      "2026-07-02T21:00",
      "2026-07-02T22:00",
      "2026-07-02T23:00",
      "2026-07-03T00:00",
      "2026-07-03T01:00",
      "2026-07-03T02:00",
      "2026-07-03T03:00",
      "2026-07-03T04:00",
      "2026-07-03T05:00",
      "2026-07-03T06:00",
      "2026-07-03T07:00",
      "2026-07-03T08:00",
      "2026-07-03T09:00",
      "2026-07-03T10:00",
      "2026-07-03T11:00",
      "2026-07-03T12:00",
      "2026-07-03T13:00",
      "2026-07-03T14:00",
      "2026-07-03T15:00",
      "2026-07-03T16:00",
      "2026-07-03T17:00",
      "2026-07-03T18:00",
      "2026-07-03T19:00",
      "2026-07-03T20:00",
      "2026-07-03T21:00",
      "2026-07-03T22:00",
      "2026-07-03T23:00",
      "2026-07-04T00:00",
      "2026-07-04T01:00",
      "2026-07-04T02:00",
      "2026-07-04T03:00",
      "2026-07-04T04:00",
      "2026-07-04T05:00",
      "2026-07-04T06:00",
      "2026-07-04T07:00",
      "2026-07-04T08:00",
      "2026-07-04T09:00",
      "2026-07-04T10:00",
      "2026-07-04T11:00",
      "2026-07-04T12:00",
      "2026-07-04T13:00",
      "2026-07-04T14:00",
      "2026-07-04T15:00",
      "2026-07-04T16:00",
      "2026-07-04T17:00",
      "2026-07-04T18:00",
      "2026-07-04T19:00",
      "2026-07-04T20:00",
      "2026-07-04T21:00",
      "2026-07-04T22:00",
      "2026-07-04T23:00",
      "2026-07-05T00:00",
      "2026-07-05T01:00",
      "2026-07-05T02:00",
      "2026-07-05T03:00",
      "2026-07-05T04:00",
      "2026-07-05T05:00",
      "2026-07-05T06:00",
      "2026-07-05T07:00",
      "2026-07-05T08:00",
      "2026-07-05T09:00",
      "2026-07-05T10:00",
      "2026-07-05T11:00",
      "2026-07-05T12:00",
      "2026-07-05T13:00",
      "2026-07-05T14:00",
      "2026-07-05T15:00",
      "2026-07-05T16:00",
      "2026-07-05T17:00",
      "2026-07-05T18:00",
      "2026-07-05T19:00",
      "2026-07-05T20:00",
      "2026-07-05T21:00",
      "2026-07-05T22:00",
      "2026-07-05T23:00",
      "2026-07-06T00:00",
      "2026-07-06T01:00",
      "2026-07-06T02:00",
      "2026-07-06T03:00",
      "2026-07-06T04:00",
      "2026-07-06T05:00",
      "2026-07-06T06:00",
      "2026-07-06T07:00",
      "2026-07-06T08:00",
      "2026-07-06T09:00",
      "2026-07-06T10:00",
      "2026-07-06T11:00",
      "2026-07-06T12:00",
      "2026-07-06T13:00",
      "2026-07-06T14:00",
      "2026-07-06T15:00",
      "2026-07-06T16:00",
      "2026-07-06T17:00",
      "2026-07-06T18:00",
      "2026-07-06T19:00",
      "2026-07-06T20:00",
      "2026-07-06T21:00",
      "2026-07-06T22:00",
      "2026-07-06T23:00",
      "2026-07-07T00:00",
      "2026-07-07T01:00",
      "2026-07-07T02:00",
      "2026-07-07T03:00",
      "2026-07-07T04:00",
      "2026-07-07T05:00",
      "2026-07-07T06:00",
      "2026-07-07T07:00",
      "2026-07-07T08:00",
      "2026-07-07T09:00",
      "2026-07-07T10:00",
      "2026-07-07T11:00",
      "2026-07-07T12:00",
      "2026-07-07T13:00",
      "2026-07-07T14:00",
      "2026-07-07T15:00",
      "2026-07-07T16:00",
      "2026-07-07T17:00",
      "2026-07-07T18:00",
      "2026-07-07T19:00",
      "2026-07-07T20:00",
      "2026-07-07T21:00",
      "2026-07-07T22:00",
      "2026-07-07T23:00"
    ],
    "weather_code": [
      0,
      0,
      0,
      0,
      0,
      0,
      0,
      0,
      0,
      0,
      0,
      0,
      0,
      0,
      0,
      0,
      0,
      0,
      0,
      0,
      0,
      0,
      0,
      0,
      0,
      0,
      0,
      0,
      0,
      0,
      0,
      0,
      0,
      0,
      0,
      0,
      0,
      0,
      0,
      0,
      0,
      0,
      0,
      0,
      0,
      0,
      0,
      0,
      0,
      0,
      0,
      0,
      0,
      0,
      0,
      0,
      0,
      0,
      0,
      0,
      0,
      0,
      0,
      3,
      3,
      3,
      3,
      0,
      2,
      3,
      3,
      3,
      3,
      3,
      0,
      0,
      0,
      0,
      0,
      0,
      0,
      0,
      0,
      0,
      0,
      0,
      0,
      3,
      0,
      3,
      3,
      3,
      3,
      3,
      2,
      3,
      0,
      0,
      0,
      0,
      0,
      0,
      0,
      0,
      0,
      0,
      0,
      0,
      0,
      0,
      0,
      0,
      0,
      3,
      3,
      0,
      3,
      3,
      3,
      3,
      3,
      0,
      0,
      0,
      0,
      0,
      0,
      0,
      0,
      0,
      0,
      0,
      0,
      0,
      0,
      3,
      3,
      3,
      3,
      3,
      3,
      3,
      3,
      3,
      3,
      2,
      1,
      1,
      0,
      0,
      0,
      0,
      0,
      0,
      0,
      0,
      0,
      0,
      1,
      1,
      2,
      2,
      3,
      3,
      3,
      2,
      2,
      2,
      2,
      2,
      2,
      2,
      2,
      1,
      1,
      0,
      0,
      0,
      0,
      0,
      0,
      0,
      0,
      0,
      51,
      51,
      51,
      2,
      1,
      0,
      1,
      2,
      3,
      3,
      2,
      1,
      1,
      0,
      0,
      0,
      0,
      0,
      0,
      0,
      0,
      0,
      0,
      0,
      0,
      0,
      0,
      1,
      2,
      2,
      2,
      2,
      2,
      1,
      1,
      0,
      0,
      0,
      0,
      0,
      0,
      0,
      0,
      0,
      0,
      0,
      1,
      1,
      2,
      3,
      3,
      3,
      3,
      3,
      3,
      3
    ],
    "wind_direction_10m": [
      174,
      38,
      17,
      1,
      286,
      155,
      173,
      185,
      200,
      185,
      159,
      153,
      162,
      152,
      139,
      138,
      152,
      135,
      123,
      73,
      61,
      309,
      313,
      342,
      359,
      352,
      18,
      12,
      360,
      40,
      36,
      67,
      177,
      167,
      166,
      170,
      230,
      241,
      237,
      231,
      238,
      249,
      256,
      270,
      278,
      267,
      288,
      303,
      341,
      146,
      295,
      278,
      342,
      86,
      318,
      40,
      76,
      87,
      143,
      128,
      147,
      145,
      125,
      37,
      123,
      118,
      115,
      48,
      62,
      263,
      252,
      234,
      258,
      254,
      265,
      263,
      262,
      273,
      284,
      281,
      264,
      191,
      177,
      176,
      210,
      216,
      184,
      156,
      175,
      197,
      166,
      72,
      37,
      44,
      14,
      357,
      331,
      351,
      354,
      336,
      14,
      14,
      212,
      200,
      180,
      192,
      142,
      121,
      126,
      111,
      110,
      110,
      53,
      4,
      344,
      294,
      298,
      306,
      337,
      332,
      315,
      343,
      318,
      312,
      291,
      72,
      225,
      205,
      191,
      184,
      174,
      125,
      101,
      99,
      137,
      184,
      266,
      5,
      99,
      65,
      27,
      10,
      357,
      323,
      288,
      306,
      332,
      341,
      337,
      324,
      314,
      324,
      342,
      354,
      2,
      15,
      51,
      80,
      87,
      82,
      51,
      4,
      347,
      349,
      12,
      81,
      103,
      117,
      270,
      198,
      150,
      145,
      167,
      191,
      200,
      180,
      53,
      59,
      103,
      142,
      149,
      137,
      125,
      124,
      149,
      196,
      216,
      214,
      204,
      197,
      189,
      159,
      62,
      34,
      307,
      277,
      294,
      32,
      55,
      52,
      47,
      51,
      94,
      138,
      148,
      143,
      133,
      129,
      133,
      138,
      136,
      105,
      37,
      16,
      7,
      345,
      298,
      270,
      255,
      233,
      190,
      140,
      124,
      125,
      137,
      147,
      141,
      136,
      132,
      118,
      100,
      93,
      162,
      207,
      213,
      201,
      84,
      63,
      63,
      96
    ],
    "wind_gusts_10m": [
      12.8,
      17.7,
      18.8,
      23.9,
      11.9,
      4.7,
      9.8,
      13.4,
      10.7,
      13.0,
      15.4,
      13.0,
      14.5,
      13.2,
      14.3,
      16.8,
      16.6,
      13.6,
      11.0,
      9.8,
      13.9,
      8.5,
      7.6,
      9.8,
      28.4,
      21.9,
      10.1,
      22.1,
      17.2,
      14.5,
      12.5,
      3.6,
      11.2,
      12.5,
      15.0,
      24.4,
      34.9,
      40.5,
      37.8,
      32.9,
      28.2,
      30.0,
      29.5,
      31.1,
      23.5,
      21.3,
      12.1,
      16.8,
      10.3,
      5.8,
      3.1,
      6.9,
      2.5,
      4.7,
      8.1,
      7.4,
      4.7,
      6.3,
      15.0,
      17.2,
      17.2,
      22.4,
      27.5,
      19.9,
      20.0,
      19.6,
      8.2,
      7.2,
      13.0,
      5.8,
      10.7,
      12.1,
      12.1,
      5.6,
      3.8,
      5.1,
      6.9,
      12.3,
      10.3,
      7.8,
      4.9,
      7.4,
      12.3,
      12.3,
      13.4,
      15.0,
      16.1,
      17.0,
      18.8,
      10.1,
      8.3,
      16.3,
      18.6,
      16.6,
      25.7,
      20.1,
      18.8,
      15.7,
      12.3,
      11.0,
      3.1,
      1.3,
      1.6,
      4.5,
      5.4,
      4.7,
      7.2,
      10.7,
      10.7,
      10.7,
      13.4,
      12.1,
      16.8,
      11.2,
      5.6,
      7.6,
      18.6,
      17.7,
      6.7,
      8.7,
      11.0,
      15.4,
      12.3,
      9.6,
      3.1,
      2.5,
      2.9,
      5.6,
      9.4,
      12.8,
      9.2,
      16.8,
      17.7,
      19.5,
      20.8,
      21.0,
      18.8,
      15.2,
      12.3,
      11.2,
      11.0,
      10.5,
      9.8,
      9.4,
      8.7,
      8.1,
      7.6,
      6.7,
      5.6,
      4.0,
      2.9,
      1.8,
      0.9,
      1.3,
      4.5,
      8.9,
      12.5,
      13.9,
      14.3,
      14.3,
      13.9,
      13.2,
      13.6,
      17.0,
      21.9,
      24.6,
      23.9,
      21.5,
      18.1,
      13.6,
      8.5,
      4.5,
      2.5,
      1.3,
      1.6,
      3.1,
      5.6,
      8.1,
      10.3,
      12.5,
      13.6,
      12.1,
      9.6,
      9.6,
      15.9,
      25.1,
      29.8,
      25.9,
      17.7,
      11.2,
      8.7,
      7.6,
      6.7,
      4.9,
      3.1,
      1.8,
      1.3,
      1.6,
      2.0,
      2.5,
      2.9,
      3.4,
      3.6,
      4.0,
      4.5,
      4.9,
      5.4,
      7.2,
      11.6,
      17.2,
      20.4,
      18.6,
      14.5,
      11.6,
      12.3,
      14.5,
      14.8,
      11.2,
      6.0,
      2.0,
      0.7,
      0.4,
      0.9,
      1.3,
      2.2,
      3.6,
      6.3,
      9.4,
      11.4,
      10.7,
      8.7,
      7.4,
      7.8,
      9.2,
      10.7,
      13.4,
      16.6,
      17.9,
      15.4,
      11.2
    ],
    "wind_speed_10m": [
      2.0,
      13.1,
      11.2,
      14.5,
      1.6,
      4.7,
      5.6,
      8.5,
      7.1,
      8.5,
      10.6,
      9.3,
      8.7,
      10.9,
      9.5,
      13.2,
      11.9,
      4.7,
      3.7,
      6.8,
      6.9,
      5.7,
      4.9,
      6.4,
      17.2,
      12.2,
      5.2,
      11.5,
      10.1,
      8.7,
      7.7,
      2.9,
      8.3,
      9.7,
      11.3,
      12.3,
      17.5,
      28.1,
      23.3,
      21.9,
      19.2,
      19.4,
      20.7,
      20.1,
      15.1,
      11.9,
      8.5,
      10.4,
      6.2,
      4.0,
      3.2,
      6.1,
      1.4,
      3.4,
      6.7,
      3.5,
      2.8,
      4.3,
      8.1,
      8.3,
      9.1,
      11.4,
      8.7,
      10.1,
      14.8,
      14.8,
      12.2,
      15.4,
      10.4,
      1.8,
      4.5,
      1.9,
      4.3,
      6.5,
      4.9,
      5.6,
      4.7,
      4.5,
      3.7,
      2.3,
      2.0,
      2.3,
      4.9,
      6.1,
      8.8,
      10.7,
      12.6,
      17.4,
      15.0,
      10.8,
      6.7,
      5.9,
      8.6,
      10.3,
      16.4,
      13.2,
      13.8,
      12.0,
      9.2,
      6.1,
      3.7,
      1.8,
      2.1,
      2.6,
      4.3,
      5.3,
      3.7,
      6.0,
      6.9,
      7.6,
      10.0,
      10.5,
      8.9,
      10.5,
      7.4,
      8.3,
      8.6,
      5.0,
      8.5,
      5.8,
      4.1,
      3.7,
      6.7,
      7.0,
      4.3,
      2.8,
      1.3,
      4.2,
      5.9,
      6.3,
      4.5,
      4.7,
      7.1,
      9.0,
      7.9,
      6.3,
      3.4,
      8.5,
      9.7,
      9.4,
      12.3,
      14.7,
      11.7,
      6.7,
      6.6,
      8.0,
      11.4,
      14.2,
      12.9,
      9.9,
      8.1,
      7.7,
      8.7,
      9.2,
      7.4,
      4.4,
      3.2,
      5.2,
      8.3,
      9.5,
      7.8,
      9.9,
      12.4,
      9.6,
      4.3,
      2.7,
      2.1,
      0.5,
      0.7,
      0.7,
      1.8,
      2.7,
      3.0,
      3.4,
      3.3,
      1.3,
      2.2,
      3.9,
      4.1,
      6.8,
      10.4,
      13.1,
      16.4,
      17.1,
      13.4,
      14.4,
      19.6,
      21.3,
      21.1,
      18.9,
      12.5,
      4.3,
      3.8,
      3.2,
      2.2,
      3.6,
      2.2,
      2.1,
      4.3,
      5.1,
      4.9,
      4.3,
      3.6,
      5.7,
      8.4,
      10.1,
      11.2,
      12.6,
      14.9,
      17.1,
      16.1,
      10.2,
      12.6,
      18.4,
      15.5,
      8.6,
      5.3,
      5.1,
      4.4,
      3.4,
      2.5,
      3.5,
      4.8,
      4.7,
      3.6,
      3.7,
      5.7,
      8.7,
      10.5,
      9.9,
      9.1,
      7.4,
      5.2,
      12.8,
      17.0,
      9.3,
      6.7,
      14.3,
      10.8,
      2.2
    ]
  },
  "latest": {
    "best_window": "Evening",
    "best_window_gust_mph": 11.5,
    "best_window_precipitation_probability_max": 0.0,
    "best_window_wind_mph": 5.1,
    "chop_proxy_ft": 0.6,
    "crowding_penalty": 8,
    "date": "2026-06-28",
    "grade": "B",
    "grade_before_wind_cap": "B",
    "grade_caps": [
      "wind_best_case_b"
    ],
    "precipitation_probability_max": 0.0,
    "report": "Live forecast is connected. Lake shape, wind-shadow, depth scoring, danger restrictions, and final chop model are pending for this lake.",
    "score": 80,
    "score_before_wind_cap": 80,
    "summary": "Catalog forecast from Open-Meteo until lake-specific model assets are added.",
    "temperature_2m_max": 86,
    "temperature_2m_min": 57,
    "weather_code": 0,
    "wind_direction_deg": 133,
    "wind_direction_label": "SE",
    "wind_gust_max_mph": 14.5,
    "wind_speed_max_mph": 14.5
  },
  "model_status": {
    "chop_height": "proxy_only_not_measured",
    "danger_restrictions": "pending",
    "depth_scoring": "pending",
    "lake_shape": "pending",
    "wind_shadow": "pending"
  },
  "source": {
    "daily_fill_url": "https://api.open-meteo.com/v1/forecast?latitude=40.43769&longitude=-105.035144&daily=weather_code%2Ctemperature_2m_max%2Ctemperature_2m_min%2Cprecipitation_probability_max%2Cwind_speed_10m_max%2Cwind_direction_10m_dominant&hourly=temperature_2m%2Cprecipitation_probability%2Cwind_speed_10m%2Cwind_gusts_10m%2Cwind_direction_10m%2Cweather_code&temperature_unit=fahrenheit&wind_speed_unit=mph&timezone=America%2FDenver&forecast_days=10",
    "hourly_url": null,
    "points_url": null,
    "url": "https://api.open-meteo.com/v1/forecast?latitude=40.43769&longitude=-105.035144&daily=weather_code%2Ctemperature_2m_max%2Ctemperature_2m_min%2Cprecipitation_probability_max%2Cwind_speed_10m_max%2Cwind_direction_10m_dominant&hourly=temperature_2m%2Cprecipitation_probability%2Cwind_speed_10m%2Cwind_gusts_10m%2Cwind_direction_10m%2Cweather_code&temperature_unit=fahrenheit&wind_speed_unit=mph&timezone=America%2FDenver&forecast_days=10",
    "weather": "Open-Meteo forecast API"
  },
  "spot": {
    "latitude": 40.43769,
    "location": "CO",
    "longitude": -105.035144,
    "name": "Boyd Lake",
    "slug": "boyd-lake"
  },
  "ten_day": [
    {
      "best_window": "Evening",
      "best_window_gust_mph": 11.5,
      "best_window_precipitation_probability_max": 0.0,
      "best_window_wind_mph": 5.1,
      "chop_proxy_ft": 0.6,
      "crowding_penalty": 8,
      "date": "2026-06-28",
      "grade": "B",
      "grade_before_wind_cap": "B",
      "grade_caps": [
        "wind_best_case_b"
      ],
      "precipitation_probability_max": 0.0,
      "score": 80,
      "score_before_wind_cap": 80,
      "summary": "Catalog forecast from Open-Meteo until lake-specific model assets are added.",
      "temperature_2m_max": 86,
      "temperature_2m_min": 57,
      "weather_code": 0,
      "wind_direction_deg": 133,
      "wind_direction_label": "SE",
      "wind_gust_max_mph": 14.5,
      "wind_speed_max_mph": 14.5
    },
    {
      "best_window": "Early morning",
      "best_window_gust_mph": 9.1,
      "best_window_precipitation_probability_max": 0.0,
      "best_window_wind_mph": 7.0,
      "chop_proxy_ft": 1.3,
      "crowding_penalty": 0,
      "date": "2026-06-29",
      "grade": "B",
      "grade_before_wind_cap": "B",
      "grade_caps": [
        "wind_best_case_b"
      ],
      "precipitation_probability_max": 0.0,
      "score": 82,
      "score_before_wind_cap": 82,
      "summary": "Catalog forecast from Open-Meteo until lake-specific model assets are added.",
      "temperature_2m_max": 86,
      "temperature_2m_min": 57,
      "weather_code": 0,
      "wind_direction_deg": 258,
      "wind_direction_label": "WSW",
      "wind_gust_max_mph": 28.1,
      "wind_speed_max_mph": 28.1
    },
    {
      "best_window": "Early morning",
      "best_window_gust_mph": 6.1,
      "best_window_precipitation_probability_max": 0.0,
      "best_window_wind_mph": 3.5,
      "chop_proxy_ft": 0.6,
      "crowding_penalty": 0,
      "date": "2026-06-30",
      "grade": "A",
      "grade_before_wind_cap": "A",
      "grade_caps": [],
      "precipitation_probability_max": 14.0,
      "score": 94,
      "score_before_wind_cap": 94,
      "summary": "Catalog forecast from Open-Meteo until lake-specific model assets are added.",
      "temperature_2m_max": 94,
      "temperature_2m_min": 52,
      "weather_code": 3,
      "wind_direction_deg": 102,
      "wind_direction_label": "ESE",
      "wind_gust_max_mph": 15.4,
      "wind_speed_max_mph": 15.4
    },
    {
      "best_window": "Early morning",
      "best_window_gust_mph": 6.7,
      "best_window_precipitation_probability_max": 1.0,
      "best_window_wind_mph": 2.2,
      "chop_proxy_ft": 0.7,
      "crowding_penalty": 0,
      "date": "2026-07-01",
      "grade": "A",
      "grade_before_wind_cap": "A",
      "grade_caps": [],
      "precipitation_probability_max": 14.0,
      "score": 94,
      "score_before_wind_cap": 94,
      "summary": "Catalog forecast from Open-Meteo until lake-specific model assets are added.",
      "temperature_2m_max": 93,
      "temperature_2m_min": 62,
      "weather_code": 3,
      "wind_direction_deg": 204,
      "wind_direction_label": "SSW",
      "wind_gust_max_mph": 17.4,
      "wind_speed_max_mph": 17.4
    },
    {
      "best_window": "Early morning",
      "best_window_gust_mph": 4.9,
      "best_window_precipitation_probability_max": 1.0,
      "best_window_wind_mph": 4.1,
      "chop_proxy_ft": 0.5,
      "crowding_penalty": 0,
      "date": "2026-07-02",
      "grade": "A",
      "grade_before_wind_cap": "A",
      "grade_caps": [],
      "precipitation_probability_max": 11.0,
      "score": 94,
      "score_before_wind_cap": 94,
      "summary": "Catalog forecast from Open-Meteo until lake-specific model assets are added.",
      "temperature_2m_max": 96,
      "temperature_2m_min": 62,
      "weather_code": 3,
      "wind_direction_deg": 6,
      "wind_direction_label": "N",
      "wind_gust_max_mph": 13.8,
      "wind_speed_max_mph": 13.8
    },
    {
      "best_window": "Early morning",
      "best_window_gust_mph": 12.9,
      "best_window_precipitation_probability_max": 0.0,
      "best_window_wind_mph": 5.2,
      "chop_proxy_ft": 0.6,
      "crowding_penalty": 0,
      "date": "2026-07-03",
      "grade": "B",
      "grade_before_wind_cap": "A",
      "grade_caps": [
        "wind_best_case_b"
      ],
      "precipitation_probability_max": 4.0,
      "score": 84,
      "score_before_wind_cap": 86,
      "summary": "Catalog forecast from Open-Meteo until lake-specific model assets are added.",
      "temperature_2m_max": 98,
      "temperature_2m_min": 65,
      "weather_code": 3,
      "wind_direction_deg": 37,
      "wind_direction_label": "NE",
      "wind_gust_max_mph": 14.7,
      "wind_speed_max_mph": 14.7
    },
    {
      "best_window": "Late morning",
      "best_window_gust_mph": 8.6,
      "best_window_precipitation_probability_max": 0.0,
      "best_window_wind_mph": 5.0,
      "chop_proxy_ft": 0.6,
      "crowding_penalty": 20,
      "date": "2026-07-04",
      "grade": "B",
      "grade_before_wind_cap": "B",
      "grade_caps": [
        "wind_best_case_b"
      ],
      "precipitation_probability_max": 6.0,
      "score": 72,
      "score_before_wind_cap": 72,
      "summary": "Catalog forecast from Open-Meteo until lake-specific model assets are added.",
      "temperature_2m_max": 95,
      "temperature_2m_min": 68,
      "weather_code": 3,
      "wind_direction_deg": 355,
      "wind_direction_label": "N",
      "wind_gust_max_mph": 14.2,
      "wind_speed_max_mph": 14.2
    },
    {
      "best_window": "Early morning",
      "best_window_gust_mph": 5.6,
      "best_window_precipitation_probability_max": 3.0,
      "best_window_wind_mph": 2.5,
      "chop_proxy_ft": 1.0,
      "crowding_penalty": 8,
      "date": "2026-07-05",
      "grade": "A",
      "grade_before_wind_cap": "A",
      "grade_caps": [],
      "precipitation_probability_max": 22.0,
      "score": 86,
      "score_before_wind_cap": 86,
      "summary": "Catalog forecast from Open-Meteo until lake-specific model assets are added.",
      "temperature_2m_max": 96,
      "temperature_2m_min": 58,
      "weather_code": 51,
      "wind_direction_deg": 173,
      "wind_direction_label": "S",
      "wind_gust_max_mph": 21.3,
      "wind_speed_max_mph": 21.3
    },
    {
      "best_window": "Early morning",
      "best_window_gust_mph": 3.3,
      "best_window_precipitation_probability_max": 0.0,
      "best_window_wind_mph": 4.3,
      "chop_proxy_ft": 0.8,
      "crowding_penalty": 0,
      "date": "2026-07-06",
      "grade": "A",
      "grade_before_wind_cap": "A",
      "grade_caps": [],
      "precipitation_probability_max": 19.0,
      "score": 94,
      "score_before_wind_cap": 94,
      "summary": "Catalog forecast from Open-Meteo until lake-specific model assets are added.",
      "temperature_2m_max": 100,
      "temperature_2m_min": 60,
      "weather_code": 3,
      "wind_direction_deg": 90,
      "wind_direction_label": "E",
      "wind_gust_max_mph": 18.4,
      "wind_speed_max_mph": 18.4
    },
    {
      "best_window": "Early morning",
      "best_window_gust_mph": 2.4,
      "best_window_precipitation_probability_max": 1.0,
      "best_window_wind_mph": 4.0,
      "chop_proxy_ft": 0.7,
      "crowding_penalty": 0,
      "date": "2026-07-07",
      "grade": "A",
      "grade_before_wind_cap": "A",
      "grade_caps": [],
      "precipitation_probability_max": 28.0,
      "score": 94,
      "score_before_wind_cap": 94,
      "summary": "Catalog forecast from Open-Meteo until lake-specific model assets are added.",
      "temperature_2m_max": 102,
      "temperature_2m_min": 63,
      "weather_code": 3,
      "wind_direction_deg": 142,
      "wind_direction_label": "SE",
      "wind_gust_max_mph": 17.0,
      "wind_speed_max_mph": 17.0
    }
  ]
}
